Metadata-Version: 2.4
Name: httpcore-eager-response
Version: 1.0.8.3
Summary: A minimal low-level HTTP client.
Project-URL: Documentation, https://www.encode.io/httpcore
Project-URL: Homepage, https://www.encode.io/httpcore/
Project-URL: Source, https://github.com/encode/httpcore
Author-email: Tom Christie <tom@tomchristie.com>, Kim Minjong <make.dirty.code@gmail.com>
License-Expression: BSD-3-Clause
License-File: LICENSE.md
Classifier: Development Status :: 3 - Alpha
Classifier: Environment :: Web Environment
Classifier: Framework :: AsyncIO
Classifier: Framework :: Trio
Classifier: Intended Audience :: Developers
Classifier: License :: OSI Approved :: BSD License
Classifier: Operating System :: OS Independent
Classifier: Programming Language :: Python :: 3
Classifier: Programming Language :: Python :: 3 :: Only
Classifier: Programming Language :: Python :: 3.8
Classifier: Programming Language :: Python :: 3.9
Classifier: Programming Language :: Python :: 3.10
Classifier: Programming Language :: Python :: 3.11
Classifier: Programming Language :: Python :: 3.12
Classifier: Topic :: Internet :: WWW/HTTP
Requires-Python: >=3.8
Requires-Dist: certifi
Requires-Dist: h11<0.15,>=0.13
Provides-Extra: asyncio
Requires-Dist: anyio<5.0,>=4.0; extra == 'asyncio'
Provides-Extra: http2
Requires-Dist: h2<5,>=3; extra == 'http2'
Provides-Extra: socks
Requires-Dist: socksio==1.*; extra == 'socks'
Provides-Extra: trio
Requires-Dist: trio<1.0,>=0.22.0; extra == 'trio'
